I2S_master_AXI_S/rtl/S_I2S_M_AXI_S.vhd
library ieee;
use ieee.std_logic_1164.all;
use ieee.numeric_std.all;

entity s_i2s_m_axis_s is
    generic(
        G_WITDH : integer := 16
    );
    port(
        sck : in std_logic;
        lrck : in std_logic;
        sdata : in std_logic;
        rst : in std_logic; 

        m_axi_s_tdata : out std_logic_vector(G_WITDH-1 downto 0);
        m_axi_s_tvalid : out std_logic; 
        m_axi_s_tready : in std_logic
    );

end entity;

architecture rtl of s_i2s_m_axis_s is
    type state is (RESET, RIGHT, LEFT, IDLE);
    signal FSM : state;
    signal tdata : std_logic_vector(G_WITDH-1 downto 0);
    signal tvalid : std_logic;
    signal data : std_logic_vector(G_WITDH-1 downto 0);
    signal lrck_store : std_logic;
begin 
    process(sck, rst)
    begin
        if rst='1' then
            FSM <= RESET;
        else
            if rising_edge(sck) then
                if m_axi_s_tready = '1' then
                    tvalid <= '1';
                end if;

                case FSM is
                    when RESET =>
                        tvalid <= '0';
                        tdata <= (others => '0');
                        lrck_store <= lrck;
                        data <= (others => '0');
                        FSM <= IDLE;
                    
                    when IDLE =>
                        lrck_store <= lrck;
                        if lrck /= lrck_store then
                            if lrck = '1' then 
                                FSM <= RIGHT;
                            else
                                FSM <= LEFT;
                            end if; 
                        end if;
                    
                    when LEFT =>
                        lrck_store <= lrck;

                        data <= data(data'high-1 downto 0) & sdata;
                        
                        if lrck_store /= lrck then
                            tdata <= data;
                            tvalid <= '1';
                            FSM <= RIGHT;
                        end if;
                    
                    when RIGHT =>
                        lrck_store <= lrck;

                        data <= data(data'high-1 downto 0) & sdata;
                        
                        if lrck_store /= lrck then
                            tdata <= data;
                            tvalid <= '1';
                            FSM <= LEFT; 
                        end if; 
                        
                        
                end case;
            end if; 
        end if; 
    end process;

    m_axi_s_tvalid <= tvalid;
    m_axi_s_tdata <= tdata;

end rtl;

I2S_master_AXI_S/sim/anyname.vcd
$date
  Fri Sep 12 15:08:05 2025
$end
$version
  GHDL v0
$end
$timescale
  1 ps
$end
$scope module standard $end
$upscope $end
$scope module std_logic_1164 $end
$upscope $end
$scope module numeric_std $end
$upscope $end
$scope module s_i2s_m_axis_s $end
$var reg 1 ! sck $end
$var reg 1 " lrck $end
$var reg 1 # sdata $end
$var reg 1 $ rst $end
$var reg 16 % m_axi_s_tdata[15:0] $end
$var reg 1 & m_axi_s_tvalid $end
$var reg 1 ' m_axi_s_tready $end
$comment fsm is not handled $end
$var reg 16 ( tdata[15:0] $end
$var reg 1 ) tvalid $end
$var reg 16 * data[15:0] $end
$var reg 1 + lrck_store $end
$upscope $end
$enddefinitions $end
#0
1!
U"
U#
1$
bUUUUUUUUUUUUUUUU %
U&
0'
bUUUUUUUUUUUUUUUU (
U)
bUUUUUUUUUUUUUUUU *
U+
#5000
0!
#10000
1!
0$
#15000
0!
#20000
1!
b0000000000000000 %
0&
1'
b0000000000000000 (
0)
b0000000000000000 *
#25000
0!
#30000
1!
1&
1)
#35000
0!
#40000
1!
0"
0#
#45000
0!
#50000
1!
0+
#55000
0!
#60000
1!
1#
#65000
0!
#70000
1!
b0000000000000001 *
#75000
0!
#80000
1!
b0000000000000011 *
#85000
0!
#90000
1!
b0000000000000111 *
#95000
0!
#100000
1!
0#
b0000000000001111 *
#105000
0!
#110000
1!
1#
b0000000000011110 *
#115000
0!
#120000
1!
b0000000000111101 *
#125000
0!
#130000
1!
b0000000001111011 *
#135000
0!
#140000
1!
b0000000011110111 *
#145000
0!
#150000
1!
b0000000111101111 *
#155000
0!
#160000
1!
b0000001111011111 *
#165000
0!
#170000
1!
0#
b0000011110111111 *
#175000
0!
#180000
1!
b0000111101111110 *
#185000
0!
#190000
1!
b0001111011111100 *
#195000
0!
#200000
1!
1#
b0011110111111000 *
#205000
0!
#210000
1!
1"
0#
b0111101111110001 *
#215000
0!
#220000
1!
b0111101111110001 %
b0111101111110001 (
b1111011111100010 *
1+
#225000
0!
#230000
1!
b1110111111000100 *
#235000
0!
#240000
1!
1#
b1101111110001000 *
#245000
0!
#250000
1!
b1011111100010001 *
#255000
0!
#260000
1!
b0111111000100011 *
#265000
0!
#270000
1!
b1111110001000111 *
#275000
0!
#280000
1!
0#
b1111100010001111 *
#285000
0!
#290000
1!
b1111000100011110 *
#295000
0!
#300000
1!
b1110001000111100 *
#305000
0!
#310000
1!
b1100010001111000 *
#315000
0!
#320000
1!
1#
b1000100011110000 *
#325000
0!
#330000
1!
0#
b0001000111100001 *
#335000
0!
#340000
1!
1#
b0010001111000010 *
#345000
0!
#350000
1!
0#
b0100011110000101 *
#355000
0!
#360000
1!
1#
b1000111100001010 *
#365000
0!
#370000
1!
0"
b0001111000010101 *
#375000
0!
#380000
1!
0#
b0001111000010101 %
b0001111000010101 (
b0011110000101011 *
0+
#385000
0!
#390000
1!
b0111100001010110 *
#395000
0!
#400000
1!
1#
b1111000010101100 *
#405000
0!
#410000
1!
0#
b1110000101011001 *
#415000
0!
#420000
1!
1#
b1100001010110010 *
#425000
0!
#430000
1!
0#
b1000010101100101 *
#435000
0!
#440000
1!
b0000101011001010 *
#445000
0!
#450000
1!
b0001010110010100 *
#455000
0!
#460000
1!
1#
b0010101100101000 *
#465000
0!
#470000
1!
0#
b0101011001010001 *
#475000
0!
#480000
1!
b1010110010100010 *
#485000
0!
#490000
1!
b0101100101000100 *
#495000
0!
#500000
1!
1#
b1011001010001000 *
#505000
0!
#510000
1!
b0110010100010001 *
#515000
0!
#520000
1!
0#
b1100101000100011 *
#525000
0!
#530000
1!
1"
b1001010001000110 *
#535000
0!
#540000
1!
b1001010001000110 %
b1001010001000110 (
b0010100010001100 *
1+
#545000
0!
#550000
1!
1#
b0101000100011000 *
#555000
0!
#560000
1!
b1010001000110001 *
#565000
0!
#570000
1!
0#
b0100010001100011 *
#575000
0!
#580000
1!
1#
b1000100011000110 *
#585000
0!
#590000
1!
b0001000110001101 *
#595000
0!
#600000
1!
b0010001100011011 *
#605000
0!
#610000
1!
0#
b0100011000110111 *
#615000
0!
#620000
1!
1#
b1000110001101110 *
#625000
0!
#630000
1!
0#
b0001100011011101 *
#635000
0!
#640000
1!
b0011000110111010 *
#645000
0!
#650000
1!
b0110001101110100 *
#655000
0!
#660000
1!
1#
b1100011011101000 *
#665000
0!
#670000
1!
0#
b1000110111010001 *
#675000
0!
#680000
1!
b0001101110100010 *
#685000
0!
#690000
1!
b0011011101000100 *
