I2C_test/rtl/i2c_test.vhd
library ieee;
use ieee.std_logic_1164.all;
use ieee.numeric_std.all;

entity i2c_test is
    port(
        -- whisbone master signals
        wb_clk_i : in std_logic;
        wb_rst_i : in std_logic := '0'; -- synchronous active high reset !
        arst_i : in std_logic := '0';
        wb_adr_o : out std_logic_vector(2 downto 0);
        wb_dat_i : in std_logic_vector(7 downto 0);
        wb_dat_o : out std_logic_vector(7 downto 0);
        wb_we_o : out std_logic;
        wb_stb_o : out std_logic;
        wb_cyc_o : out std_logic;
        wb_ack_i : in std_logic;
        wb_inta_o : in std_logic;
        send_test : in std_logic;

        debug : out natural
    );

end i2c_test;

architecture rtl of i2c_test is
    type state is (RESET, IDLE, SEND, INIT);
    signal fsm : state;
    constant slave_addr : std_logic_vector(6 downto 0) := "1100111";
    constant txr_addr : std_logic_vector(2 downto 0) := "011";
    type init_array is array (natural range <>) of std_logic_vector(7 downto 0);
    signal wb_stb : std_logic;

    constant init_data_list : init_array := (
        x"02",  -- PRER 
        x"C0"   -- CTR
    );

    constant init_addr_list : init_array :=(
        x"00", -- PRER 
        x"02"  -- CTR
    );

    type send_data is array (natural range <>) of std_logic_vector(7 downto 0);

    constant test_data : send_data := (
        slave_addr & '0', -- potentiel problème au niveau du bit d'écriture, à tester !
        X"90",
        X"C4",
        X"50"
    );

    constant test_addr : send_data := (
        X"03",
        X"04",
        X"03",
        X"04"
    );
    
    begin
    
    process(wb_clk_i, arst_i)
        variable i : natural range 0 to 15 := 0;
    begin
        if arst_i = '1' then
            fsm <= RESET;
        else
            if rising_edge(wb_clk_i) then
                case fsm is
                    when RESET =>
                        wb_adr_o <= (others => '0');
                        wb_dat_o <= (others => '0'); 
                        wb_cyc_o <= '0';
                        wb_stb <= '0';
                        wb_we_o <= '0';

                        fsm <= INIT;
                        i := 0;

                    when INIT =>
                            wb_adr_o <= init_addr_list(i)(2 downto 0);
                            wb_dat_o <= init_data_list(i);
                            wb_we_o <= '1'; 
                            wb_cyc_o <= '1';
                        if i = 0 then 
                            wb_stb <= '1';
                        end if; 

                        if wb_stb = '1' then
                            wb_stb <= '0';
                            --wb_cyc_o <= '0';
                        end if;

                        if wb_ack_i = '1' then
                            wb_stb <= '1';
                            i := i+1;
                            if i = 2 then
                                fsm <= IDLE;
                                wb_adr_o <= (others => '0');
                                wb_dat_o <= (others => '0');
                                wb_we_o <= '0';
                                wb_cyc_o <= '0';
                                wb_stb <= '0';
                                i := 0;
                            end if;
                        end if;

                    when IDLE =>
                        if send_test = '1' then
                            fsm <= SEND;
                        end if; 
                    
                    when SEND =>
                        wb_adr_o <= test_addr(i)(2 downto 0);
                        wb_dat_o <= test_data(i);
                        wb_we_o <= '1';
                        wb_cyc_o <= '1';
                        wb_stb <= '1';

                        if wb_stb = '1' then
                            wb_stb <= '0';
                            --wb_cyc_o <= '0';
                        end if;

                        if wb_ack_i = '1' then
                            i := i+1;
                            if i = 4 then
                                i := 0;
                                fsm <= IDLE;
                                wb_adr_o <= (others => '0');
                                wb_dat_o <= (others => '0');
                                wb_we_o <= '0';
                                wb_cyc_o <= '0';
                                wb_stb <= '0';
                            end if;
                        end if;
                end case;
                if wb_rst_i = '1' then
                    fsm <= RESET;
                end if;
                debug <= i;
             end if;
        end if;
    end process;
    wb_stb_o <= wb_stb; 
end rtl;

I2C_test/testbench/anyname.vcd
$date
  Sat Sep 27 21:18:38 2025
$end
$version
  GHDL v0
$end
$timescale
  1 ps
$end
$scope module standard $end
$upscope $end
$scope module std_logic_1164 $end
$upscope $end
$scope module numeric_std $end
$upscope $end
$scope module i2c_test $end
$var reg 1 ! wb_clk_i $end
$var reg 1 " wb_rst_i $end
$var reg 1 # arst_i $end
$var reg 3 $ wb_adr_o[2:0] $end
$var reg 8 % wb_dat_i[7:0] $end
$var reg 8 & wb_dat_o[7:0] $end
$var reg 1 ' wb_we_o $end
$var reg 1 ( wb_stb_o $end
$var reg 1 ) wb_cyc_o $end
$var reg 1 * wb_ack_i $end
$var reg 1 + wb_inta_o $end
$var reg 1 , send_test $end
$var integer 32 - debug $end
$comment fsm is not handled $end
$var reg 1 . wb_stb $end
$upscope $end
$enddefinitions $end
#0
1!
0"
1#
bUUU $
b00000000 %
bUUUUUUUU &
U'
U(
U)
0*
U+
U,
b0 -
U.
#83350
0!
#166700
1!
#250050
0!
#333400
1!
#416750
0!
#500100
1!
#583450
0!
#666800
1!
#750150
0!
#833500
1!
#916850
0!
#1000000
0#
#1000200
1!
b000 $
b00000000 &
0'
0(
0)
0.
#1083550
0!
#1166900
1!
b00000010 &
1'
1(
1)
1.
#1250250
0!
#1333600
1!
0(
1*
0.
#1416950
0!
#1500300
1!
1(
0*
b1 -
1.
#1583650
0!
#1667000
1!
b010 $
b11000000 &
0(
1*
0.
#1750350
0!
#1833700
1!
b000 $
b00000000 &
0'
0)
0*
b0 -
#1917050
0!
#2000400
1!
#2083750
0!
#2167100
1!
#2250450
0!
#2333800
1!
#2417150
0!
#2500500
1!
#2583850
0!
#2667200
1!
#2750550
0!
#2833900
1!
#2917250
0!
#3000600
1!
#3083950
0!
#3167300
1!
#3250650
0!
#3334000
1!
#3417350
0!
#3500700
1!
#3584050
0!
#3667400
1!
#3750750
0!
#3834100
1!
#3917450
0!
#4000800
1!
#4084150
0!
#4167500
1!
#4250850
0!
#4334200
1!
#4417550
0!
#4500900
1!
#4584250
0!
#4667600
1!
0,
#4750950
0!
#4834300
1!
#4917650
0!
#5001000
1!
#5084350
0!
#5167700
1!
#5251050
0!
#5334400
1!
#5417750
0!
#5501100
1!
#5584450
0!
#5667800
1!
#5751150
0!
#5834500
1!
#5917850
0!
#6001200
1!
#6084550
0!
#6167900
1!
#6251250
0!
#6334600
1!
#6417950
0!
#6501300
1!
#6584650
0!
#6668000
1!
#6751350
0!
#6834700
1!
#6918050
0!
#7001400
1!
#7084750
0!
#7168100
1!
#7251450
0!
#7334800
1!
#7418150
0!
#7501500
1!
#7584850
0!
#7668200
1!
#7751550
0!
#7834900
1!
#7918250
0!
#8001600
1!
1,
#8084950
0!
#8168300
1!
#8251650
0!
#8335000
1!
b011 $
b11001110 &
1'
1(
1)
1.
#8418350
0!
#8501700
1!
0(
1*
0.
#8585050
0!
#8668400
1!
1(
0*
b1 -
1.
#8751750
0!
#8835100
1!
b100 $
b10010000 &
0(
1*
0.
#8918450
0!
#9001800
1!
1(
0*
b10 -
1.
#9085150
0!
#9168500
1!
b011 $
b11000100 &
0(
1*
0.
#9251850
0!
#9335200
1!
1(
0*
b11 -
1.
#9418550
0!
#9501900
1!
b100 $
b01010000 &
0(
1*
0.
#9585250
0!
#9668600
1!
b000 $
b00000000 &
0'
0)
0*
b0 -
#9751950
0!
#9835300
1!
#9918650
0!
#10002000
1!
b011 $
b11001110 &
1'
1(
1)
1.
#10085350
0!
#10168700
1!
0(
1*
0.
#10252050
0!
#10335400
1!
1(
0*
b1 -
1.
#10418750
0!
#10502100
1!
b100 $
b10010000 &
0(
1*
0.
#10585450
0!
#10668800
1!
1(
0*
b10 -
1.
#10752150
0!
#10835500
1!
b011 $
b11000100 &
0(
1*
0.
#10918850
0!
#11002200
1!
1(
0*
b11 -
1.
#11085550
0!
#11168900
1!
b100 $
b01010000 &
0(
1*
0.
#11252250
0!
#11335600
1!
b000 $
b00000000 &
0'
0)
0*
b0 -
#11418950
0!
#11502300
1!
#11585650
0!
#11669000
1!
b011 $
b11001110 &
1'
1(
1)
1.
#11752350
0!
#11835700
1!
0(
1*
0.
#11919050
0!
#12002400
1!
1(
0*
b1 -
1.
#12085750
0!
#12169100
1!
b100 $
b10010000 &
0(
1*
0.
#12252450
0!
#12335800
1!
1(
0*
b10 -
1.
#12419150
0!
#12502500
1!
b011 $
b11000100 &
0(
1*
0.
#12585850
0!
#12669200
1!
1(
0*
b11 -
1.
#12752550
0!
#12835900
1!
b100 $
b01010000 &
0(
1*
0.
#12919250
0!
#13002600
1!
b000 $
b00000000 &
0'
0)
0*
b0 -
#13085950
0!
#13169300
1!
#13252650
0!
#13336000
1!
b011 $
b11001110 &
1'
1(
1)
1.
#13419350
0!
#13502700
1!
0(
1*
0.
#13586050
0!
#13669400
1!
1(
0*
b1 -
1.
#13752750
0!
#13836100
1!
b100 $
b10010000 &
0(
1*
0.
#13919450
0!
#14002800
1!
1(
0*
b10 -
1.
#14086150
0!
#14169500
1!
b011 $
b11000100 &
0(
1*
0.
#14252850
0!
#14336200
1!
1(
0*
b11 -
1.
#14419550
0!
#14502900
1!
b100 $
b01010000 &
0(
1*
0.
#14586250
0!
#14669600
1!
b000 $
b00000000 &
0'
0)
0*
b0 -
#14752950
0!
#14836300
1!
#14919650
0!
#15003000
1!
b011 $
b11001110 &
1'
1(
1)
1.
#15086350
0!
#15169700
1!
0(
1*
0.
#15253050
0!
#15336400
1!
1(
0*
b1 -
1.
#15419750
0!
#15503100
1!
b100 $
b10010000 &
0(
1*
0.
#15586450
0!
#15669800
1!
1(
0*
b10 -
1.
#15753150
0!
#15836500
1!
b011 $
b11000100 &
0(
1*
0.
#15919850
0!
#16003200
1!
1(
0*
b11 -
1.
#16086550
0!
#16169900
1!
b100 $
b01010000 &
0(
1*
0.
#16253250
0!
#16336600
1!
b000 $
b00000000 &
0'
0)
0*
b0 -
#16419950
0!
#16503300
1!
#16586650
0!
#16670000
1!
b011 $
b11001110 &
1'
1(
1)
1.
#16753350
0!
#16836700
1!
0(
1*
0.
#16920050
0!
#17003400
1!
1(
0*
b1 -
1.
#17086750
0!
#17170100
1!
b100 $
b10010000 &
0(
1*
0.
#17253450
0!
#17336800
1!
1(
0*
b10 -
1.
#17420150
0!
#17503500
1!
b011 $
b11000100 &
0(
1*
0.
#17586850
0!
#17670200
1!
1(
0*
b11 -
1.
#17753550
0!
#17836900
1!
b100 $
b01010000 &
0(
1*
0.
#17920250
0!
#18003600
1!
b000 $
b00000000 &
0'
0)
0*
b0 -
#18086950
0!
#18170300
1!
#18253650
0!
#18337000
1!
b011 $
b11001110 &
1'
1(
1)
1.
#18420350
0!
#18503700
1!
0(
1*
0.
#18587050
0!
#18670400
1!
1(
0*
b1 -
1.
#18753750
0!
#18837100
1!
b100 $
b10010000 &
0(
1*
0.
#18920450
0!
#19003800
1!
1(
0*
b10 -
1.
#19087150
0!
#19170500
1!
b011 $
b11000100 &
0(
1*
0.
#19253850
0!
#19337200
1!
1(
0*
b11 -
1.
#19420550
0!
#19503900
1!
b100 $
b01010000 &
0(
1*
0.
#19587250
0!
#19670600
1!
b000 $
b00000000 &
0'
0)
0*
b0 -
#19753950
0!
#19837300
1!
#19920650
0!
#20004000
1!
b011 $
b11001110 &
1'
1(
1)
1.
#20087350
0!
#20170700
1!
0(
1*
0.
#20254050
0!
#20337400
1!
1(
0*
b1 -
1.
#20420750
0!
#20504100
1!
b100 $
b10010000 &
0(
1*
0.
#20587450
0!
#20670800
1!
1(
0*
b10 -
1.
#20754150
0!
#20837500
1!
b011 $
b11000100 &
0(
1*
0.
#20920850
0!
#21004200
1!
1(
0*
b11 -
1.
#21087550
0!
#21170900
1!
b100 $
b01010000 &
0(
1*
0.
#21254250
0!
#21337600
1!
b000 $
b00000000 &
0'
0)
0*
b0 -
#21420950
0!
#21504300
1!
#21587650
0!
#21671000
1!
b011 $
b11001110 &
1'
1(
1)
1.
#21754350
0!
#21837700
1!
0(
1*
0.
#21921050
0!
#22004400
1!
1(
0*
b1 -
1.
#22087750
0!
#22171100
1!
b100 $
b10010000 &
0(
1*
0.
#22254450
0!
#22337800
1!
1(
0*
b10 -
1.
#22421150
0!
#22504500
1!
b011 $
b11000100 &
0(
1*
0.
#22587850
0!
#22671200
1!
1(
0*
b11 -
1.
#22754550
0!
#22837900
1!
b100 $
b01010000 &
0(
1*
0.
#22921250
0!
#23004600
1!
b000 $
b00000000 &
0'
0)
0*
b0 -
#23087950
0!
#23171300
1!
#23254650
0!
#23338000
1!
b011 $
b11001110 &
1'
1(
1)
1.
#23421350
0!
#23504700
1!
0(
1*
0.
#23588050
0!
#23671400
1!
1(
0*
b1 -
1.
#23754750
0!
#23838100
1!
b100 $
b10010000 &
0(
1*
0.
#23921450
0!
#24004800
1!
1(
0*
b10 -
1.
#24088150
0!
#24171500
1!
b011 $
b11000100 &
0(
1*
0.
#24254850
0!
#24338200
1!
1(
0*
b11 -
1.
#24421550
0!
#24504900
1!
b100 $
b01010000 &
0(
1*
0.
#24588250
0!
#24671600
1!
b000 $
b00000000 &
0'
0)
b0 -
